AcdhUriNormRules/AcdhUriNormRules.py
AcdhUriNormRules/__init__.py
AcdhUriNormRules/rules.json
tests/__init__.py
tests/test_normalizer.py
acdh_uri_norm_rules-2.0.0.dist-info/LICENSE
acdh_uri_norm_rules-2.0.0.dist-info/METADATA
acdh_uri_norm_rules-2.0.0.dist-info/WHEEL
acdh_uri_norm_rules-2.0.0.dist-info/top_level.txt
acdh_uri_norm_rules-2.0.0.dist-info/RECORD
