Metadata-Version: 2.1
Name: acdh-uri-norm-rules
Version: 2.0.0
Summary: A set of URI normalization rules used by the ACDH
Home-page: https://github.com/acdh-oeaw/UriNormRules
Author: Mateusz Żółtak
Author-email: mzoltak@oeaw.ac.at
License: UNKNOWN
Platform: UNKNOWN
Classifier: Programming Language :: Python :: 3
Classifier: License :: OSI Approved :: MIT License
Classifier: Operating System :: OS Independent
